{
  "project_info": {
    "project_number": "421121472639",
    "firebase_url": "https://trackmymusic-29180.firebaseio.com",
    "project_id": "trackmymusic-29180",
    "storage_bucket": "trackmymusic-29180.appspot.com"
  },
  "client": [
    {
      "client_info": {
        "mobilesdk_app_id": "1:421121472639:android:11894064d801394c",
        "android_client_info": {
          "package_name": "com.bhadrasoft.trackmymusic"
        }
      },
      "oauth_client": [
        {
          "client_id": "421121472639-0pv6nnnnqf8es7br5sk544h7fbf32686.apps.googleusercontent.com",
          "client_type": 1,
          "android_info": {
            "package_name": "com.bhadrasoft.trackmymusic",
            "certificate_hash": "73f6e2e52434a0e010f3a7ec24f308eb720fddde"
          }
        },
        {
          "client_id": "421121472639-81ob5k6t0v8qmn9uhlnslk2th1bauivk.apps.googleusercontent.com",
          "client_type": 3
        }
      ],
      "api_key": [
        {
          "current_key": "AIzaSyAiTysgVXut0PvL5tTbTLvbYq95yRj9PAU"
        }
      ],
      "services": {
        "analytics_service": {
          "status": 1
        },
        "appinvite_service": {
          "status": 2,
          "other_platform_oauth_client": [
            {
              "client_id": "421121472639-81ob5k6t0v8qmn9uhlnslk2th1bauivk.apps.googleusercontent.com",
              "client_type": 3
            }
          ]
        },
        "ads_service": {
          "status": 2
        }
      }
    }
  ],
  "configuration_version": "1"
}